softcropper/__init__.py
softcropper/cli.py
softcropper/processor.py
softcropper-0.1.9.dist-info/licenses/LICENSE
softcropper-0.1.9.dist-info/METADATA
softcropper-0.1.9.dist-info/WHEEL
softcropper-0.1.9.dist-info/entry_points.txt
softcropper-0.1.9.dist-info/top_level.txt
softcropper-0.1.9.dist-info/RECORD
