Metadata-Version: 2.4
Name: softcropper
Version: 0.1.9
Summary: Resize and blur-pad photos to square format for photos
Home-page: https://github.com/khaledalam/softcropper
Author: Khaled Alam
License: MIT
Project-URL: Source, https://github.com/khaledalam/softcropper
Project-URL: Tracker, https://github.com/khaledalam/softcropper/issues
Classifier: Programming Language :: Python :: 3
Classifier: License :: OSI Approved :: MIT License
Classifier: Operating System :: OS Independent
Requires-Python: >=3.7
License-File: LICENSE
Requires-Dist: opencv-python
Requires-Dist: numpy
Dynamic: author
Dynamic: classifier
Dynamic: description
Dynamic: description-content-type
Dynamic: home-page
Dynamic: license
Dynamic: license-file
Dynamic: project-url
Dynamic: requires-dist
Dynamic: requires-python
Dynamic: summary
